cgpmgr/__init__.py
cgpmgr/cli.py
cgpmgr-1.12.dist-info/LICENSE
cgpmgr-1.12.dist-info/METADATA
cgpmgr-1.12.dist-info/WHEEL
cgpmgr-1.12.dist-info/entry_points.txt
cgpmgr-1.12.dist-info/top_level.txt
cgpmgr-1.12.dist-info/RECORD
